yandex2lightroom/__init__.py
yandex2lightroom/__main__.py
yandex2lightroom/default_locations.py
yandex2lightroom/downloader.py
yandex2lightroom/exiftool.py
yandex2lightroom/image_download.py
yandex2lightroom/parse.py
yandex2lightroom-1.1.1.0.dist-info/LICENSE.txt
yandex2lightroom-1.1.1.0.dist-info/METADATA
yandex2lightroom-1.1.1.0.dist-info/WHEEL
yandex2lightroom-1.1.1.0.dist-info/entry_points.txt
yandex2lightroom-1.1.1.0.dist-info/top_level.txt
yandex2lightroom-1.1.1.0.dist-info/RECORD
