Metadata-Version: 2.1
Name: yandex2lightroom
Version: 1.1.1.0
Summary: Python Script to download images from Yandex.Images for the use in Adobe Lightroom.
Home-page: https://github.com/sto3014/yandex2lightroom-git
Download-URL: https://github.com/sto3014/yandex2lightroom-git/archive/main.zip
Author: Dieter Stockhausen
Author-email: dieter@schwingenhausen.at
License: MIT
Keywords: yandex images download save terminal command-line scrapper lightroom
Classifier: Development Status :: 4 - Beta
Classifier: Intended Audience :: Developers
Classifier: License :: OSI Approved :: MIT License
Classifier: Programming Language :: Python :: 3.9
License-File: LICENSE.txt
Requires-Dist: beautifulsoup4 >=4.10.0
Requires-Dist: certifi >=2023.7.22
Requires-Dist: chardet >=4.0.0
Requires-Dist: dataclasses >=0.6
Requires-Dist: dataclasses-json >=0.5.14
Requires-Dist: idna >=3.4
Requires-Dist: lxml >=4.9.3
Requires-Dist: marshmallow >=3.20.1
Requires-Dist: marshmallow-enum >=1.5.1
Requires-Dist: mypy-extensions >=0.4.3
Requires-Dist: pyopenssl >=23.0.0
Requires-Dist: requests >=2.31.0
Requires-Dist: selenium >=4.13.0
Requires-Dist: selenium-wire >=5.1.0
Requires-Dist: soupsieve >=2.5
Requires-Dist: stringcase >=1.2.0
Requires-Dist: typing >=3.7.4
Requires-Dist: typing-extensions >=3.10.0.2
Requires-Dist: typing-inspect >=0.9.0
Requires-Dist: urllib3 >=2.0.5
Requires-Dist: webdriver-auto-update >=1.1.0
